zetta_backend_toolkit/__init__.py
zetta_backend_toolkit/Logger/__init__.py
zetta_backend_toolkit/Logger/logger_methods.py
zetta_backend_toolkit/Logger/logger_middleware.py
zetta_backend_toolkit/RateLimit/__init__.py
zetta_backend_toolkit/RateLimit/ratelimit_middleware.py
zetta_backend_toolkit/Translation/__init__.py
zetta_backend_toolkit/Translation/translation_middleware.py
zetta_backend_toolkit-0.1.4.dist-info/LICENSE
zetta_backend_toolkit-0.1.4.dist-info/METADATA
zetta_backend_toolkit-0.1.4.dist-info/WHEEL
zetta_backend_toolkit-0.1.4.dist-info/top_level.txt
zetta_backend_toolkit-0.1.4.dist-info/RECORD
