Metadata-Version: 2.1
Name: zetta-backend-toolkit
Version: 0.1.4
Summary: Un toolkit Backend para FastAPI
Home-page: https://github.com/gonzageraci/Zetta-Backend-Toolkit
Author: Gonzalo Geraci
Author-email: gonza.geraci@gmail.com
Classifier: Programming Language :: Python :: 3
Classifier: License :: OSI Approved :: MIT License
Classifier: Operating System :: OS Independent
Requires-Python: >=3.10
License-File: LICENSE
Requires-Dist: fastapi
Requires-Dist: starlette
